ai/backend/agent/VERSION
ai/backend/agent/__init__.py
ai/backend/agent/affinity_map.py
ai/backend/agent/agent.py
ai/backend/agent/alloc_map.py
ai/backend/agent/etcd.py
ai/backend/agent/exception.py
ai/backend/agent/fs.py
ai/backend/agent/kernel.py
ai/backend/agent/monitor.py
ai/backend/agent/proxy.py
ai/backend/agent/py.typed
ai/backend/agent/resources.py
ai/backend/agent/runtime.py
ai/backend/agent/server.py
ai/backend/agent/stats.py
ai/backend/agent/types.py
ai/backend/agent/utils.py
ai/backend/agent/cli/__init__.py
ai/backend/agent/cli/__main__.py
ai/backend/agent/cli/config.py
ai/backend/agent/cli/context.py
ai/backend/agent/cli/dependencies.py
ai/backend/agent/cli/health.py
ai/backend/agent/cli/start_server.py
ai/backend/agent/config/__init__.py
ai/backend/agent/config/unified.py
ai/backend/agent/dependencies/__init__.py
ai/backend/agent/dependencies/composer.py
ai/backend/agent/dependencies/bootstrap/__init__.py
ai/backend/agent/dependencies/bootstrap/composer.py
ai/backend/agent/dependencies/bootstrap/config.py
ai/backend/agent/dependencies/bootstrap/etcd.py
ai/backend/agent/dependencies/bootstrap/redis_config.py
ai/backend/agent/dependencies/infrastructure/__init__.py
ai/backend/agent/dependencies/infrastructure/composer.py
ai/backend/agent/dependencies/infrastructure/docker.py
ai/backend/agent/dependencies/infrastructure/redis.py
ai/backend/agent/docker/__init__.py
ai/backend/agent/docker/agent.py
ai/backend/agent/docker/backendai-socket-relay.img.aarch64.tar.gz
ai/backend/agent/docker/backendai-socket-relay.img.x86_64.tar.gz
ai/backend/agent/docker/backendai-socket-relay.version.txt
ai/backend/agent/docker/files.py
ai/backend/agent/docker/intrinsic.py
ai/backend/agent/docker/kernel.py
ai/backend/agent/docker/linuxkit-metadata-proxy-worker.aarch64.bin
ai/backend/agent/docker/linuxkit-metadata-proxy-worker.x86_64.bin
ai/backend/agent/docker/linuxkit-nsenter.img.aarch64.tar.gz
ai/backend/agent/docker/linuxkit-nsenter.img.x86_64.tar.gz
backend_ai_agent-26.1.0.dist-info/METADATA
backend_ai_agent-26.1.0.dist-info/WHEEL
backend_ai_agent-26.1.0.dist-info/entry_points.txt
backend_ai_agent-26.1.0.dist-info/namespace_packages.txt
backend_ai_agent-26.1.0.dist-info/top_level.txt
backend_ai_agent-26.1.0.dist-info/RECORD
