Metadata-Version: 2.4
Name: backend.ai-agent
Version: 26.1.0
Summary: Backend.AI Agent
Home-page: https://github.com/lablup/backend.ai
Author: Lablup Inc. and contributors
License: LGPLv3
Project-URL: Documentation, https://docs.backend.ai/
Project-URL: Source, https://github.com/lablup/backend.ai
Classifier: Intended Audience :: Developers
Classifier: Operating System :: MacOS :: MacOS X
Classifier: Operating System :: POSIX :: Linux
Classifier: Programming Language :: Python
Classifier: Programming Language :: Python :: 3
Classifier: Environment :: No Input/Output (Daemon)
Classifier: Topic :: Scientific/Engineering
Classifier: Topic :: Software Development
Classifier: Development Status :: 5 - Production/Stable
Classifier: Programming Language :: Python :: 3.13
Classifier: License :: OSI Approved :: GNU Lesser General Public License v3 or later (LGPLv3+)
Requires-Python: >=3.13,<3.14
Requires-Dist: aiodocker==0.24.0
Requires-Dist: aiofiles~=24.1.0
Requires-Dist: aiohttp_cors~=0.8.1
Requires-Dist: aiohttp~=3.13.3
Requires-Dist: aiomonitor~=0.7.0
Requires-Dist: aiotools~=2.2.3
Requires-Dist: async_timeout~=4.0
Requires-Dist: attrs>=25.3
Requires-Dist: backend.ai-cli==26.1.0
Requires-Dist: backend.ai-common==26.1.0
Requires-Dist: backend.ai-kernel-binary==26.1.0
Requires-Dist: backend.ai-kernel-helper==26.1.0
Requires-Dist: backend.ai-kernel==26.1.0
Requires-Dist: backend.ai-krunner-static-gnu==4.4.0
Requires-Dist: backend.ai-logging==26.1.0
Requires-Dist: backend.ai-plugin==26.1.0
Requires-Dist: cachetools~=5.5.0
Requires-Dist: callosum~=1.0.3
Requires-Dist: cattrs~=24.1.1
Requires-Dist: click~=8.1.7
Requires-Dist: etcd-client-py~=0.5.1
Requires-Dist: janus~=2.0
Requires-Dist: kubernetes-asyncio~=33.3.0
Requires-Dist: kubernetes~=33.1.0
Requires-Dist: more-itertools~=10.5.0
Requires-Dist: networkx~=3.3.0
Requires-Dist: prometheus-client~=0.21.1
Requires-Dist: psutil~=7.0
Requires-Dist: pydantic[email]~=2.11.3
Requires-Dist: pyzmq~=26.4
Requires-Dist: ruamel.yaml~=0.18.10
Requires-Dist: setproctitle~=1.3.5
Requires-Dist: setuptools~=80.0.0
Requires-Dist: tenacity>=9.0
Requires-Dist: tomlkit~=0.13.2
Requires-Dist: trafaret~=2.1
Requires-Dist: types-aiofiles
Requires-Dist: types-cachetools
Requires-Dist: types-psutil
Requires-Dist: types-setuptools
Requires-Dist: uvloop~=0.22.1; sys_platform != "Windows"
Dynamic: author
Dynamic: classifier
Dynamic: description
Dynamic: description-content-type
Dynamic: home-page
Dynamic: license
Dynamic: project-url
Dynamic: requires-dist
Dynamic: requires-python
Dynamic: summary
